hugo_nbconvert/__main__.py
hugo_nbconvert/date.py
hugo_nbconvert/glob_hugo_ipynb.py
hugo_nbconvert/global_config.py
hugo_nbconvert/hugo_fix.py
hugo_nbconvert/main.py
hugo_nbconvert/markdown_convert.py
hugo_nbconvert/markdown_processor.py
hugo_nbconvert/new.py
hugo_nbconvert/resource.py
hugo_nbconvert/run.py
hugo_nbconvert/tools.py
soda_hugo_nbconvert-2025.5.24.0.dist-info/METADATA
soda_hugo_nbconvert-2025.5.24.0.dist-info/WHEEL
soda_hugo_nbconvert-2025.5.24.0.dist-info/entry_points.txt
soda_hugo_nbconvert-2025.5.24.0.dist-info/licenses/LICENSE
soda_hugo_nbconvert-2025.5.24.0.dist-info/RECORD
